sparkouille/__init__.py
sparkouille-0.1.6.dist-info/DESCRIPTION.rst
sparkouille-0.1.6.dist-info/METADATA
sparkouille-0.1.6.dist-info/RECORD
sparkouille-0.1.6.dist-info/WHEEL
sparkouille-0.1.6.dist-info/metadata.json
sparkouille-0.1.6.dist-info/top_level.txt
