Metadata-Version: 2.0
Name: sparkouille
Version: 0.1.6
Summary: Ways to productionize machine learning predictions
Home-page: http://www.xavierdupre.fr/app/sparkouille/helpsphinx/index.html
Author: Xavier Dupré
Author-email: xavier.dupre@gmail.com
License: MIT
Download-URL: https://github.com/sdpython/sparkouille/
Keywords: sparkouille,Xavier Dupré
Platform: UNKNOWN
Classifier: Programming Language :: Python :: 3
Classifier: Intended Audience :: Developers
Classifier: Topic :: Scientific/Engineering
Classifier: Topic :: Education
Classifier: License :: OSI Approved :: MIT License
Classifier: Development Status :: 5 - Production/Stable
Requires-Dist: pyspark
